build/lib/build/lib/build/lib/zhlyr/serialize.c
build/lib/build/lib/build/lib/zhlyr/serialize.cp312-win_amd64.pyd
build/lib/build/lib/build/lib/zhlyr/serialize.cpython-312-x86_64-linux-gnu.so
build/lib/build/lib/zhlyr/serialize.c
build/lib/build/lib/zhlyr/serialize.cp312-win_amd64.pyd
build/lib/build/lib/zhlyr/serialize.cpython-312-x86_64-linux-gnu.so
build/lib/zhlyr/serialize.c
build/lib/zhlyr/serialize.cp312-win_amd64.pyd
build/lib/zhlyr/serialize.cpython-312-x86_64-linux-gnu.so
zhlyr/__init__.py
zhlyr/recosnize.py
zhlyr/serialize.c
zhlyr/serialize.cp312-win_amd64.pyd
zhlyr/serialize.cpython-312-x86_64-linux-gnu.so
zhlyr/zhlyr.py
zhlyr-5.1.dist-info/METADATA
zhlyr-5.1.dist-info/WHEEL
zhlyr-5.1.dist-info/top_level.txt
zhlyr-5.1.dist-info/RECORD
