Metadata-Version: 2.1
Name: zhlyr
Version: 5.1
Summary: Python library for music handling
Home-page: https://gaoc3.github.io/zhlyr/
Author: Mtsky
Author-email: secon2636@gmail.com
License: MIT
Keywords: lyrics,music,shazam,serialize,serializer,recognize
Classifier: Development Status :: 1 - Planning
Classifier: Intended Audience :: Developers
Classifier: License :: OSI Approved :: MIT License
Classifier: Programming Language :: Python :: 3.9
Classifier: Programming Language :: Python :: 3
Classifier: Operating System :: Unix
Classifier: Operating System :: MacOS :: MacOS X
Classifier: Operating System :: Microsoft :: Windows
Requires-Python: >=3.9
Requires-Dist: requests
Requires-Dist: shazamio
Requires-Dist: shazam
Requires-Dist: cython
